cnct/__init__.py
cnct/rql.py
connect/client/__init__.py
connect/client/constants.py
connect/client/contrib/__init__.py
connect/client/contrib/locust/__init__.py
connect/client/contrib/locust/user.py
connect/client/exceptions.py
connect/client/fluent.py
connect/client/help_formatter.py
connect/client/logger.py
connect/client/mixins.py
connect/client/models/__init__.py
connect/client/models/base.py
connect/client/models/exceptions.py
connect/client/models/iterators.py
connect/client/models/mixins.py
connect/client/models/resourceset.py
connect/client/openapi.py
connect/client/rql/__init__.py
connect/client/rql/base.py
connect/client/rql/utils.py
connect/client/testing/__init__.py
connect/client/testing/fixtures.py
connect/client/testing/fluent.py
connect/client/testing/models/__init__.py
connect/client/testing/models/base.py
connect/client/testing/models/mixins.py
connect/client/testing/models/resourceset.py
connect/client/utils.py
connect/client/version.py
connect_openapi_client-34.0.dist-info/LICENSE
connect_openapi_client-34.0.dist-info/METADATA
connect_openapi_client-34.0.dist-info/WHEEL
connect_openapi_client-34.0.dist-info/entry_points.txt
connect_openapi_client-34.0.dist-info/RECORD
