Metadata-Version: 2.1
Name: connect-openapi-client
Version: 34.0
Summary: Connect Python OpenAPI Client
Home-page: https://connect.cloudblue.com
License: Apache-2.0
Keywords: fulfillment,api,client,openapi,utility,connect,cloudblue
Author: CloudBlue
Requires-Python: >=3.9,<4
Classifier: Development Status :: 5 - Production/Stable
Classifier: Environment :: Console
Classifier: Intended Audience :: Developers
Classifier: License :: OSI Approved :: Apache Software License
Classifier: Operating System :: OS Independent
Classifier: Programming Language :: Python :: 3
Classifier: Programming Language :: Python :: 3.9
Classifier: Programming Language :: Python :: 3.10
Classifier: Programming Language :: Python :: 3.11
Classifier: Programming Language :: Python :: 3.12
Classifier: Programming Language :: Python :: 3.13
Classifier: Topic :: Software Development :: Libraries
Classifier: Topic :: Utilities
Requires-Dist: PyYAML (>=5.3.1)
Requires-Dist: asgiref (>=3.3.4,<4.0.0)
Requires-Dist: connect-markdown-renderer (>=3,<4)
Requires-Dist: httpx (>=0.23)
Requires-Dist: importlib-metadata (>=6.6,<7.0)
Requires-Dist: inflect (>=4.1)
Requires-Dist: pytest-httpx (>=0.27,<0.30)
Requires-Dist: requests (>=2.23)
Requires-Dist: responses (>=0.14.0,<1)
Project-URL: Documentation, https://connect-openapi-client.readthedocs.io/en/latest/
Project-URL: Repository, https://github.com/cloudblue/connect-python-openapi-client
